{
  "patients": [
    {
      "id": 1,
      "full name": "ESSAHELI Kaouthar",
      "number": "055555555",
      "last_visit": "03/10/2024 12H45",
      "status": "Completed"
    },
    {
      "id": 2,
      "full name": "ESSAHELI Maria",
      "number": "055555555",
      "last_visit": "03/10/2024 12H45",
      "status": "Pending"
    },
    {
      "id": 3,
      "full name": "RASSI Mohammed",
      "number": "055555555",
      "last_visit": "03/10/2024 12H45",
      "status": "Canceled"
    },
    {
      "id": 4,
      "full name": "RANA Leyna",
      "number": "055555555",
      "last_visit": "03/10/2024 12H45",
      "status": "Completed"
    }
  ]
}
